coininfo_georg/__init__.py
coininfo_georg/info.py
coininfo_georg-1.1.1.dist-info/METADATA
coininfo_georg-1.1.1.dist-info/WHEEL
coininfo_georg-1.1.1.dist-info/top_level.txt
coininfo_georg-1.1.1.dist-info/RECORD
