Metadata-Version: 2.1
Name: coininfo-georg
Version: 1.1.1
Requires-Dist: requests ==2.31.0
